sharelock_utils
