Metadata-Version: 1.1
Name: sharelock-utils
Version: 0.3.49
Summary: Simple utils for Sharelock
Home-page: UNKNOWN
Author: Rani
Author-email: rani@snip.today
License: MIT
Platform: UNKNOWN
Classifier: Programming Language :: Python :: 3.6
